README.md
setup.py
src/earth_brain_engine/__init__.py
src/earth_brain_engine/config.py
src/earth_brain_engine/constant.py
src/earth_brain_engine/engine.py
src/earth_brain_engine/tool.py
src/earth_brain_engine.egg-info/PKG-INFO
src/earth_brain_engine.egg-info/SOURCES.txt
src/earth_brain_engine.egg-info/dependency_links.txt
src/earth_brain_engine.egg-info/requires.txt
src/earth_brain_engine.egg-info/top_level.txt
src/earth_brain_engine/test/__init__.py
src/earth_brain_engine/test/test_engine_server.py