Metadata-Version: 2.1
Name: earth-brain-engine
Version: 1.1
Summary: Earth Brain Engine Package
Home-page: http://127.0.0.1/geovis_earth_brain_engine/
Author: LiuDonggang
Author-email: 1437309904@qq.com
License: MIT
